[
  {
    "id": 1,
    "price": 6,
    "gold": 60,
    "give_gold": 10,
    "key_id": 1
  },
  {
    "id": 2,
    "price": 30,
    "gold": 300,
    "give_gold": 40,
    "key_id": 2
  },
  {
    "id": 3,
    "price": 68,
    "gold": 680,
    "give_gold": 140,
    "key_id": 3
  },
  {
    "id": 4,
    "price": 128,
    "gold": 1280,
    "give_gold": 380,
    "key_id": 4
  },
  {
    "id": 5,
    "price": 328,
    "gold": 3280,
    "give_gold": 1340,
    "key_id": 5
  },
  {
    "id": 6,
    "price": 648,
    "gold": 6480,
    "give_gold": 3600,
    "key_id": 6
  }
]